<?xml version="1.0" encoding="utf-8"?>
<Routine Name="subRFIDtoPIA" Type="RLL">
  <RLLContent>
    <Rung Type="N">
      <Text><![CDATA[SBR(StoreStackTimeStamp)NOP();]]></Text>
    </Rung>
    <Rung Type="N">
      <Comment><![CDATA[Anode Data

Layer 1 = bottom anode - part 1
Layer 9 (old 5) = top anode - part 2
Layer 5 = middle anode - part 3
]]></Comment>
      <Text><![CDATA[[COP(StackData.Layer[1].RFID_Data.Data[0],Pia.Machine.Data_Trace.Value[1],1) ,[COP(StackData.Layer[1].RFID_Data.Data[1],Pia.Machine.Data_Trace.Value[2],1) ,COP(StackData.Layer[1].RFID_Data.Data[2],Pia.Machine.Data_Trace.Value[3],1) ] ,[COP(StackData.Layer[9].RFID_Data.Data[3],Pia.Machine.Data_Trace.Value[4],1) ,COP(StackData.Layer[9].RFID_Data.Data[4],Pia.Machine.Data_Trace.Value[5],1) ] ,[COP(StackData.Layer[5].RFID_Data.Data[5],Pia.Machine.Data_Trace.Value[6],1) ,COP(StackData.Layer[5].RFID_Data.Data[6],Pia.Machine.Data_Trace.Value[7],1) ] ,[COP(StackData.Layer[1].RFID_Data.Data[7],Pia.Machine.Data_Trace.Value[8],1) ,COP(StackData.Layer[9].RFID_Data.Data[7],Pia.Machine.Data_Trace.Value[9],1) ,COP(StackData.Layer[5].RFID_Data.Data[8],Pia.Machine.Data_Trace.Value[10],1) ] ,[COP(StackData.Layer[1].RFID_Data.Data[9],Pia.Machine.Data_Trace.Value[11],1) ,COP(StackData.Layer[9].RFID_Data.Data[9],Pia.Machine.Data_Trace.Value[12],1) ,COP(StackData.Layer[5].RFID_Data.Data[10],Pia.Machine.Data_Trace.Value[13],1) ] ,[COP(StackData.Layer[1].RFID_Data.Data[11],Pia.Machine.Data_Trace.Value[14],1) ,COP(StackData.Layer[5].RFID_Data.Data[11],Pia.Machine.Data_Trace.Value[15],1) ,COP(StackData.Layer[9].RFID_Data.Data[12],Pia.Machine.Data_Trace.Value[16],1) ] ,COP(StackData.Layer[1].RFID_Data.Data[13],Pia.Machine.Data_Trace.Value[17],1) ,[COP(blank_str,str_LiPN,1) ,CONCAT(StackData.Layer[1].RFID_Data.Data[17],strcomma,str_LiPN) ,CONCAT(str_LiPN,StackData.Layer[9].RFID_Data.Data[17],str_LiPN) ,CONCAT(str_LiPN,strcomma,str_LiPN) ,CONCAT(str_LiPN,StackData.Layer[5].RFID_Data.Data[17],str_LiPN) ,COP(str_LiPN,Pia.Machine.Data_Trace.Value[18],1) ] ,[COP(blank_str,str_LiPN,1) ,CONCAT(StackData.Layer[1].RFID_Data.Data[18],strcomma,str_LiLN) ,CONCAT(str_LiLN,StackData.Layer[9].RFID_Data.Data[18],str_LiLN) ,CONCAT(str_LiLN,strcomma,str_LiLN) ,CONCAT(str_LiLN,StackData.Layer[5].RFID_Data.Data[18],str_LiLN) ,COP(str_LiLN,Pia.Machine.Data_Trace.Value[19],1) ] ,[COP(StackData.Layer[1].RFID_Data.Data[14],Pia.Machine.Data_Trace.Value[20],1) ,COP(StackData.Layer[9].RFID_Data.Data[14],Pia.Machine.Data_Trace.Value[21],1) ,COP(StackData.Layer[5].RFID_Data.Data[14],Pia.Machine.Data_Trace.Value[22],1) ] ,[COP(blank_str,str_LiBrush,1) ,CONCAT(StackData.Layer[1].RFID_Data.Data[15],strcomma,str_LiBrush) ,CONCAT(str_LiBrush,StackData.Layer[1].RFID_Data.Data[16],str_LiBrush) ,COP(str_LiBrush,Pia.Machine.Data_Trace.Value[23],1) ] ,[COP(blank_str,str_LiBrush,1) ,CONCAT(StackData.Layer[9].RFID_Data.Data[15],strcomma,str_LiBrush) ,CONCAT(str_LiBrush,StackData.Layer[9].RFID_Data.Data[16],str_LiBrush) ,COP(str_LiBrush,Pia.Machine.Data_Trace.Value[24],1) ] ,[COP(blank_str,str_LiBrush,1) ,CONCAT(StackData.Layer[5].RFID_Data.Data[15],strcomma,str_LiBrush) ,CONCAT(str_LiBrush,StackData.Layer[5].RFID_Data.Data[16],str_LiBrush) ,COP(str_LiBrush,Pia.Machine.Data_Trace.Value[25],1) ] ,[COP(StackData.Layer[1].RFID_Data.Data[19],Pia.Machine.Data_Trace.Value[26],1) ,COP(StackData.Layer[9].RFID_Data.Data[19],Pia.Machine.Data_Trace.Value[27],1) ,COP(StackData.Layer[5].RFID_Data.Data[19],Pia.Machine.Data_Trace.Value[28],1) ] ,[COP(StackData.Layer[1].RFID_Data.Data[20],Pia.Machine.Data_Trace.Value[29],1) ,COP(StackData.Layer[9].RFID_Data.Data[20],Pia.Machine.Data_Trace.Value[30],1) ,COP(StackData.Layer[5].RFID_Data.Data[20],Pia.Machine.Data_Trace.Value[31],1) ] ];]]></Text>
    </Rung>
    <Rung Type="N">
      <Comment><![CDATA[Cathode Data

layer 3 and 7 = cathodes]]></Comment>
      <Text><![CDATA[[[COP(StackData.Layer[3].RFID_Data.Data[0],Pia.Machine.Data_Trace.Value[32],1) ,COP(StackData.Layer[7].RFID_Data.Data[0],Pia.Machine.Data_Trace.Value[33],1) ] ,[[COP(blank_str,str_Collector_PNs,1) ,CONCAT(StackData.Layer[3].RFID_Data.Data[1],strcomma,str_Collector_PNs) ,CONCAT(str_Collector_PNs,StackData.Layer[7].RFID_Data.Data[1],str_Collector_PNs) ,COP(str_Collector_PNs,Pia.Machine.Data_Trace.Value[34],1) ] ,COP(StackData.Layer[7].RFID_Data.Data[1],Pia.Machine.Data_Trace.Value[35],1) ] ,[[COP(blank_str,str_Collector_LNs,1) ,CONCAT(StackData.Layer[3].RFID_Data.Data[2],strcomma,str_Collector_LNs) ,CONCAT(str_Collector_LNs,StackData.Layer[7].RFID_Data.Data[2],str_Collector_LNs) ,CONCAT(str_Collector_LNs,k_str_LotQuantity2,Pia.Machine.Data_Trace.Value[82]) CONCAT(str_Collector_LNs,k_str_LotQuantity,str_Collector_LNs) ,COP(str_Collector_LNs,Pia.Machine.Data_Trace.Value[36],1) ] ,COP(StackData.Layer[7].RFID_Data.Data[2],Pia.Machine.Data_Trace.Value[37],1) ] ,[[MID(StackData.Layer[3].RFID_Data.Data[4],4,1,strTempTime) STOD(strTempTime,CPA_DATETIME_3_4.Yr) ,MID(StackData.Layer[3].RFID_Data.Data[4],2,6,strTempTime) STOD(strTempTime,CPA_DATETIME_3_4.Mo) ,MID(StackData.Layer[3].RFID_Data.Data[4],2,9,strTempTime) STOD(strTempTime,CPA_DATETIME_3_4.Da) ,MID(StackData.Layer[3].RFID_Data.Data[4],2,12,strTempTime) STOD(strTempTime,CPA_DATETIME_3_4.Hr) ,MID(StackData.Layer[3].RFID_Data.Data[4],2,15,strTempTime) STOD(strTempTime,CPA_DATETIME_3_4.Min) ,MID(StackData.Layer[3].RFID_Data.Data[4],2,18,strTempTime) STOD(strTempTime,CPA_DATETIME_3_4.Sec) ] ,[MID(StackData.Layer[7].RFID_Data.Data[4],4,1,strTempTime) STOD(strTempTime,CPA_DATETIME_7_4.Yr) ,MID(StackData.Layer[7].RFID_Data.Data[4],2,6,strTempTime) STOD(strTempTime,CPA_DATETIME_7_4.Mo) ,MID(StackData.Layer[7].RFID_Data.Data[4],2,9,strTempTime) STOD(strTempTime,CPA_DATETIME_7_4.Da) ,MID(StackData.Layer[7].RFID_Data.Data[4],2,12,strTempTime) STOD(strTempTime,CPA_DATETIME_7_4.Hr) ,MID(StackData.Layer[7].RFID_Data.Data[4],2,15,strTempTime) STOD(strTempTime,CPA_DATETIME_7_4.Min) ,MID(StackData.Layer[7].RFID_Data.Data[4],2,18,strTempTime) STOD(strTempTime,CPA_DATETIME_7_4.Sec) ] ,T_LES(T_LES_CPA_DATETIME,CPA_DATETIME_3_4,CPA_DATETIME_7_4) ] ,XIC(T_LES_CPA_DATETIME.Out) [AOI_INGENIO_DT_CONV(CPA_DateTimeStamp_Convert,StackData.Layer[3].RFID_Data.Data[4],Pia.Machine.Data_Trace.Value[38]) ,AOI_INGENIO_DT_CONV(CPA_DateTimeStamp_Convert,StackData.Layer[7].RFID_Data.Data[4],Pia.Machine.Data_Trace.Value[39]) ] ,XIO(T_LES_CPA_DATETIME.Out) [AOI_INGENIO_DT_CONV(CPA_DateTimeStamp_Convert,StackData.Layer[3].RFID_Data.Data[4],Pia.Machine.Data_Trace.Value[39]) ,AOI_INGENIO_DT_CONV(CPA_DateTimeStamp_Convert,StackData.Layer[7].RFID_Data.Data[4],Pia.Machine.Data_Trace.Value[38]) ] ,[COP(StackData.Layer[3].RFID_Data.Data[3],Pia.Machine.Data_Trace.Value[40],1) ,COP(StackData.Layer[7].RFID_Data.Data[3],Pia.Machine.Data_Trace.Value[41],1) ] ,[COP(StackData.Layer[3].RFID_Data.Data[5],Pia.Machine.Data_Trace.Value[42],1) ,COP(StackData.Layer[7].RFID_Data.Data[5],Pia.Machine.Data_Trace.Value[43],1) ] ,[COP(StackData.Layer[3].RFID_Data.Data[13],Pia.Machine.Data_Trace.Value[44],1) ,COP(StackData.Layer[7].RFID_Data.Data[13],Pia.Machine.Data_Trace.Value[45],1) ] ,[COP(blank_str,str_Sep_PNs,1) ,CONCAT(StackData.Layer[3].RFID_Data.Data[14],strcomma,str_Sep_PNs) ,CONCAT(str_Sep_PNs,StackData.Layer[3].RFID_Data.Data[16],str_Sep_PNs) ,COP(str_Sep_PNs,Pia.Machine.Data_Trace.Value[46],1) ] ,[COP(blank_str,str_Sep_PNs,1) ,CONCAT(StackData.Layer[7].RFID_Data.Data[14],strcomma,str_Sep_PNs) ,CONCAT(str_Sep_PNs,StackData.Layer[7].RFID_Data.Data[16],str_Sep_PNs) ,COP(str_Sep_PNs,Pia.Machine.Data_Trace.Value[47],1) ] ,[COP(blank_str,str_Sep_LNs,1) ,CONCAT(StackData.Layer[3].RFID_Data.Data[15],strcomma,str_Sep_LNs) ,CONCAT(str_Sep_LNs,StackData.Layer[3].RFID_Data.Data[17],str_Sep_LNs) ,COP(str_Sep_LNs,Pia.Machine.Data_Trace.Value[48],1) ] ,[COP(blank_str,str_Sep_LNs,1) ,CONCAT(StackData.Layer[7].RFID_Data.Data[15],strcomma,str_Sep_LNs) ,CONCAT(str_Sep_LNs,StackData.Layer[7].RFID_Data.Data[17],str_Sep_LNs) ,COP(str_Sep_LNs,Pia.Machine.Data_Trace.Value[49],1) ] ,[COP(StackData.Layer[3].RFID_Data.Data[18],Pia.Machine.Data_Trace.Value[50],1) ,COP(StackData.Layer[3].RFID_Data.Data[19],Pia.Machine.Data_Trace.Value[78],1) ] ,[COP(StackData.Layer[7].RFID_Data.Data[18],Pia.Machine.Data_Trace.Value[51],1) ,COP(StackData.Layer[7].RFID_Data.Data[19],Pia.Machine.Data_Trace.Value[79],1) ] ,[COP(StackData.Layer[3].RFID_Data.Data[20],Pia.Machine.Data_Trace.Value[52],1) ,COP(StackData.Layer[7].RFID_Data.Data[20],Pia.Machine.Data_Trace.Value[53],1) ] ,[COP(StackData.Layer[3].RFID_Data.Data[21],Pia.Machine.Data_Trace.Value[54],1) ,COP(StackData.Layer[7].RFID_Data.Data[21],Pia.Machine.Data_Trace.Value[55],1) ] ,[COP(StackData.Layer[3].RFID_Data.Data[22],Pia.Machine.Data_Trace.Value[56],1) ,COP(StackData.Layer[7].RFID_Data.Data[22],Pia.Machine.Data_Trace.Value[57],1) ] ,[COP(StackData.Layer[3].RFID_Data.Data[6],Pia.Machine.Data_Trace.Value[58],1) ,COP(StackData.Layer[7].RFID_Data.Data[6],Pia.Machine.Data_Trace.Value[59],1) ] ,[COP(blank_str,str_Pdwr_LNs,1) ,CONCAT(StackData.Layer[3].RFID_Data.Data[7],strcomma,str_Pdwr_LNs) ,CONCAT(str_Pdwr_LNs,StackData.Layer[3].RFID_Data.Data[9],str_Pdwr_LNs) ,COP(str_Pdwr_LNs,Pia.Machine.Data_Trace.Value[60],1) ] ,[COP(blank_str,str_Pdwr_LNs,1) ,CONCAT(StackData.Layer[7].RFID_Data.Data[7],strcomma,str_Pdwr_LNs) ,CONCAT(str_Pdwr_LNs,StackData.Layer[7].RFID_Data.Data[9],str_Pdwr_LNs) ,COP(str_Pdwr_LNs,Pia.Machine.Data_Trace.Value[61],1) ] ,[COP(blank_str,str_Pdwr_PNs,1) ,CONCAT(StackData.Layer[3].RFID_Data.Data[8],strcomma,str_Pdwr_PNs) ,CONCAT(str_Pdwr_PNs,StackData.Layer[3].RFID_Data.Data[10],str_Pdwr_PNs) ,COP(str_Pdwr_PNs,Pia.Machine.Data_Trace.Value[62],1) ] ,[COP(blank_str,str_Pdwr_PNs,1) ,CONCAT(StackData.Layer[7].RFID_Data.Data[8],strcomma,str_Pdwr_PNs) ,CONCAT(str_Pdwr_PNs,StackData.Layer[7].RFID_Data.Data[10],str_Pdwr_PNs) ,COP(str_Pdwr_PNs,Pia.Machine.Data_Trace.Value[63],1) ] ,[COP(StackData.Layer[3].RFID_Data.Data[11],Pia.Machine.Data_Trace.Value[74],1) ,COP(StackData.Layer[7].RFID_Data.Data[11],Pia.Machine.Data_Trace.Value[76],1) ] ,[COP(StackData.Layer[3].RFID_Data.Data[12],Pia.Machine.Data_Trace.Value[75],1) ,COP(StackData.Layer[7].RFID_Data.Data[12],Pia.Machine.Data_Trace.Value[77],1) ] ];]]></Text>
    </Rung>
    <Rung Type="N">
      <Comment><![CDATA[Stacker Data]]></Comment>
      <Text><![CDATA[[COP(Settings.MachineESN.Value,Pia.Machine.Data_Trace.Value[64],1) ,COP(StackData.Can_Layer.Placed_Layer_Trace_Data,Pia.Machine.Data_Trace.Value[65],1) ,COP(String_Placed_InsulatorPN,Pia.Machine.Data_Trace.Value[66],1) ,COP(StackData.Insulator_Layer.Placed_Layer_Trace_Data,Pia.Machine.Data_Trace.Value[67],1) ,COP(String_Discrete_PN,Pia.Machine.Data_Trace.Value[68],1) ,COP(StackData.Layer[2].Placed_Layer_Trace_Data,Pia.Machine.Data_Trace.Value[69],1) ,COP(DiscreteDie.CurrentDieESN,Pia.Machine.Data_Trace.Value[70],1) ,COP(System.Username,Pia.Machine.Data_Trace.Value[71],1) ,XIC(StoreStackTimeStamp) COP(CurrentDateTime,Pia.Machine.Data_Trace.Value[72],1) ,CONCAT(Pia.Machine.Data_Trace.Value[48],K_str_Comma,Pia.Machine.Data_Trace.Value[80]) CONCAT(Pia.Machine.Data_Trace.Value[80],Pia.Machine.Data_Trace.Value[69],Pia.Machine.Data_Trace.Value[80]) ,CONCAT(Pia.Machine.Data_Trace.Value[3],K_str_Comma,Pia.Machine.Data_Trace.Value[81]) CONCAT(Pia.Machine.Data_Trace.Value[81],Pia.Machine.Data_Trace.Value[5],Pia.Machine.Data_Trace.Value[81]) CONCAT(Pia.Machine.Data_Trace.Value[81],K_str_Comma,Pia.Machine.Data_Trace.Value[81]) CONCAT(Pia.Machine.Data_Trace.Value[81],Pia.Machine.Data_Trace.Value[7],Pia.Machine.Data_Trace.Value[81]) ];]]></Text>
    </Rung>
    <Rung Type="N">
      <Comment><![CDATA[Total cathode collector calcs]]></Comment>
      <Text><![CDATA[[CLR(Total_Cathode_Weight) ,NEQ(Pia.Machine.Data_Trace.Value[52],K_Str_Blank) [STOR(Pia.Machine.Data_Trace.Value[52],temp) ,ADD(Total_Cathode_Weight,temp,Total_Cathode_Weight) ] ,NEQ(Pia.Machine.Data_Trace.Value[53],K_Str_Blank) [STOR(Pia.Machine.Data_Trace.Value[53],temp) ,ADD(Total_Cathode_Weight,temp,Total_Cathode_Weight) ] ,RTOS(Total_Cathode_Weight,Pia.Machine.Data_Trace.Value[73]) ];]]></Text>
    </Rung>
    <Rung Type="N">
      <Text><![CDATA[[COP(Pia.Machine.Data_Trace,HISTORIAN.Trace,1) ,COP(Pia.Machine.Trav_Numbers[0],HISTORIAN.Traveler,1) ];]]></Text>
    </Rung>
  </RLLContent>
</Routine>